AUTHORS
CHANGELOG.txt
DESCRIPTION
LICENSE
MANIFEST.in
README.rst
setup.py
cmsplugin_blog_seo_addons/__init__.py
cmsplugin_blog_seo_addons/admin.py
cmsplugin_blog_seo_addons/models.py
cmsplugin_blog_seo_addons/simple_translate.py
cmsplugin_blog_seo_addons.egg-info/PKG-INFO
cmsplugin_blog_seo_addons.egg-info/SOURCES.txt
cmsplugin_blog_seo_addons.egg-info/dependency_links.txt
cmsplugin_blog_seo_addons.egg-info/requires.txt
cmsplugin_blog_seo_addons.egg-info/top_level.txt
cmsplugin_blog_seo_addons/migrations/0001_initial.py
cmsplugin_blog_seo_addons/migrations/0002_auto__del_entryseoaddontranslation__add_seoaddontranslation__add_seoad.py
cmsplugin_blog_seo_addons/migrations/__init__.py
cmsplugin_blog_seo_addons/templatetags/__init__.py
cmsplugin_blog_seo_addons/templatetags/seo_addons_tags.py
cmsplugin_blog_seo_addons/tests/__init__.py
cmsplugin_blog_seo_addons/tests/factories.py
cmsplugin_blog_seo_addons/tests/models_tests.py
cmsplugin_blog_seo_addons/tests/runtests.py
cmsplugin_blog_seo_addons/tests/seo_addons_tags_tests.py
cmsplugin_blog_seo_addons/tests/south_settings.py
cmsplugin_blog_seo_addons/tests/test_settings.py
cmsplugin_blog_seo_addons/tests/urls.py