Metadata-Version: 1.0
Name: cmsplugin-blog-seo-addons
Version: 0.2
Summary: Allows to add meta descriptions to a cmsplugin-blog Entry.
